README.md
setup.py
pulumi_packet/__init__.py
pulumi_packet/bgp_session.py
pulumi_packet/device.py
pulumi_packet/device_network_type.py
pulumi_packet/get_device.py
pulumi_packet/get_device_bgp_neighbors.py
pulumi_packet/get_ip_block_ranges.py
pulumi_packet/get_operating_system.py
pulumi_packet/get_organization.py
pulumi_packet/get_precreated_ip_block.py
pulumi_packet/get_project.py
pulumi_packet/get_spot_market_price.py
pulumi_packet/get_spot_market_request.py
pulumi_packet/get_spotmarket_request.py
pulumi_packet/get_volume.py
pulumi_packet/ip_attachment.py
pulumi_packet/organization.py
pulumi_packet/port_vlan_attachment.py
pulumi_packet/project.py
pulumi_packet/project_ssh_key.py
pulumi_packet/provider.py
pulumi_packet/py.typed
pulumi_packet/reserved_ip_block.py
pulumi_packet/spot_market_request.py
pulumi_packet/ssh_key.py
pulumi_packet/tables.py
pulumi_packet/utilities.py
pulumi_packet/vlan.py
pulumi_packet/volume.py
pulumi_packet/volume_attachment.py
pulumi_packet.egg-info/PKG-INFO
pulumi_packet.egg-info/SOURCES.txt
pulumi_packet.egg-info/dependency_links.txt
pulumi_packet.egg-info/not-zip-safe
pulumi_packet.egg-info/requires.txt
pulumi_packet.egg-info/top_level.txt
pulumi_packet/config/__init__.py
pulumi_packet/config/vars.py