Metadata-Version: 2.1
Name: pulumi-packet
Version: 3.0.0
Summary: A Pulumi package for creating and managing Packet cloud resources.
Home-page: https://pulumi.io
License: Apache-2.0
Project-URL: Repository, https://github.com/pulumi/pulumi-packet
Keywords: pulumi packet
Platform: UNKNOWN
